[ {
  "_id" : {
    "$oid" : "67fab6d59930102295343241"
  },
  "id" : "67fab6d59930102295343241",
  "kind" : "CLOZE",
  "knowledgeId" : {
    "$oid" : "6814dafa7d73e7209a13d2dd"
  },
  "title" : "Positive and Negative Past Perfect Practice",
  "instructions" : "Escribe oraciones en 'past perfect'.",
  "translation" : "No habíamos leído el libro.",
  "theoryId" : "b1.04.Past_Perfect_Forms_1_Positive_and_Negative",
  "topicName" : "Future continuous / present perfect continuous / past perfect",
  "difficulty" : {
    "$numberDouble" : "0.0"
  },
  "retries" : {
    "$numberDouble" : "0.0"
  },
  "noScoreRetries" : {
    "$numberDouble" : "0.0"
  },
  "code" : "",
  "audioUrl" : "",
  "imageUrl" : "",
  "answerAudioUrl" : "B1.04.09.01",
  "answerImageUrl" : "",
  "miniTheory" : "",
  "successMessage" : "",
  "form" : {
    "kind" : "CLOZE",
    "incidence" : {
      "$numberDouble" : "1.0"
    },
    "label" : "",
    "name" : "",
    "sentenceParts" : [ {
      "kind" : "TEXT",
      "text" : "We",
      "options" : null
    }, {
      "kind" : "CLOZE",
      "text" : "",
      "options" : [ "hadn't read" ]
    }, {
      "kind" : "TEXT",
      "text" : "(not / read) the book.",
      "options" : null
    } ]
  }
}, {
  "_id" : {
    "$oid" : "67fab6d59930102295343242"
  },
  "id" : "67fab6d59930102295343242",
  "kind" : "CLOZE",
  "knowledgeId" : {
    "$oid" : "6814dafa7d73e7209a13d2dd"
  },
  "title" : "Positive and Negative Past Perfect Practice",
  "instructions" : "Escribe oraciones en 'past perfect'.",
  "translation" : "No habíamos hablado antes.",
  "theoryId" : "b1.04.Past_Perfect_Forms_1_Positive_and_Negative",
  "topicName" : "Future continuous / present perfect continuous / past perfect",
  "difficulty" : {
    "$numberDouble" : "0.0"
  },
  "retries" : {
    "$numberDouble" : "0.0"
  },
  "noScoreRetries" : {
    "$numberDouble" : "0.0"
  },
  "code" : "",
  "audioUrl" : "",
  "imageUrl" : "",
  "answerAudioUrl" : "B1.04.09.02",
  "answerImageUrl" : "",
  "miniTheory" : "",
  "successMessage" : "",
  "form" : {
    "kind" : "CLOZE",
    "incidence" : {
      "$numberDouble" : "1.0"
    },
    "label" : "",
    "name" : "",
    "sentenceParts" : [ {
      "kind" : "TEXT",
      "text" : "We",
      "options" : null
    }, {
      "kind" : "CLOZE",
      "text" : "",
      "options" : [ "hadn't spoken" ]
    }, {
      "kind" : "TEXT",
      "text" : "(not / speak) before.",
      "options" : null
    } ]
  }
}, {
  "_id" : {
    "$oid" : "67fab6d59930102295343243"
  },
  "id" : "67fab6d59930102295343243",
  "kind" : "CLOZE",
  "knowledgeId" : {
    "$oid" : "6814dafa7d73e7209a13d2dd"
  },
  "title" : "Positive and Negative Past Perfect Practice",
  "instructions" : "Escribe oraciones en 'past perfect'.",
  "translation" : "Ellos habían estado enfermos varias veces.",
  "theoryId" : "b1.04.Past_Perfect_Forms_1_Positive_and_Negative",
  "topicName" : "Future continuous / present perfect continuous / past perfect",
  "difficulty" : {
    "$numberDouble" : "0.0"
  },
  "retries" : {
    "$numberDouble" : "0.0"
  },
  "noScoreRetries" : {
    "$numberDouble" : "0.0"
  },
  "code" : "",
  "audioUrl" : "",
  "imageUrl" : "",
  "answerAudioUrl" : "B1.04.09.03",
  "answerImageUrl" : "",
  "miniTheory" : "",
  "successMessage" : "",
  "form" : {
    "kind" : "CLOZE",
    "incidence" : {
      "$numberDouble" : "1.0"
    },
    "label" : "",
    "name" : "",
    "sentenceParts" : [ {
      "kind" : "TEXT",
      "text" : "They",
      "options" : null
    }, {
      "kind" : "CLOZE",
      "text" : "",
      "options" : [ "had been" ]
    }, {
      "kind" : "TEXT",
      "text" : "(be) sick several times.",
      "options" : null
    } ]
  }
}, {
  "_id" : {
    "$oid" : "67fab6d59930102295343244"
  },
  "id" : "67fab6d59930102295343244",
  "kind" : "CLOZE",
  "knowledgeId" : {
    "$oid" : "6814dafa7d73e7209a13d2dd"
  },
  "title" : "Positive and Negative Past Perfect Practice",
  "instructions" : "Escribe oraciones en 'past perfect'.",
  "translation" : "Se había oscurecido.",
  "theoryId" : "b1.04.Past_Perfect_Forms_1_Positive_and_Negative",
  "topicName" : "Future continuous / present perfect continuous / past perfect",
  "difficulty" : {
    "$numberDouble" : "0.0"
  },
  "retries" : {
    "$numberDouble" : "0.0"
  },
  "noScoreRetries" : {
    "$numberDouble" : "0.0"
  },
  "code" : "",
  "audioUrl" : "",
  "imageUrl" : "",
  "answerAudioUrl" : "B1.04.09.04",
  "answerImageUrl" : "",
  "miniTheory" : "",
  "successMessage" : "",
  "form" : {
    "kind" : "CLOZE",
    "incidence" : {
      "$numberDouble" : "1.0"
    },
    "label" : "",
    "name" : "",
    "sentenceParts" : [ {
      "kind" : "TEXT",
      "text" : "It",
      "options" : null
    }, {
      "kind" : "CLOZE",
      "text" : "",
      "options" : [ "had turned" ]
    }, {
      "kind" : "TEXT",
      "text" : "(turn) dark.",
      "options" : null
    } ]
  }
}, {
  "_id" : {
    "$oid" : "67fab6d59930102295343245"
  },
  "id" : "67fab6d59930102295343245",
  "kind" : "CLOZE",
  "knowledgeId" : {
    "$oid" : "6814dafa7d73e7209a13d2dd"
  },
  "title" : "Positive and Negative Past Perfect Practice",
  "instructions" : "Escribe oraciones en 'past perfect'.",
  "translation" : "Ella no había usado sombrero.",
  "theoryId" : "b1.04.Past_Perfect_Forms_1_Positive_and_Negative",
  "topicName" : "Future continuous / present perfect continuous / past perfect",
  "difficulty" : {
    "$numberDouble" : "0.0"
  },
  "retries" : {
    "$numberDouble" : "0.0"
  },
  "noScoreRetries" : {
    "$numberDouble" : "0.0"
  },
  "code" : "",
  "audioUrl" : "",
  "imageUrl" : "",
  "answerAudioUrl" : "B1.04.09.05",
  "answerImageUrl" : "",
  "miniTheory" : "",
  "successMessage" : "",
  "form" : {
    "kind" : "CLOZE",
    "incidence" : {
      "$numberDouble" : "1.0"
    },
    "label" : "",
    "name" : "",
    "sentenceParts" : [ {
      "kind" : "TEXT",
      "text" : "She",
      "options" : null
    }, {
      "kind" : "CLOZE",
      "text" : "",
      "options" : [ "hadn't worn" ]
    }, {
      "kind" : "TEXT",
      "text" : "(not / wear) a hat.",
      "options" : null
    } ]
  }
}, {
  "_id" : {
    "$oid" : "67fab6d59930102295343246"
  },
  "id" : "67fab6d59930102295343246",
  "kind" : "CLOZE",
  "knowledgeId" : {
    "$oid" : "6814dafa7d73e7209a13d2dd"
  },
  "title" : "Positive and Negative Past Perfect Practice",
  "instructions" : "Escribe oraciones en 'past perfect'.",
  "translation" : "Él no había bebido café.",
  "theoryId" : "b1.04.Past_Perfect_Forms_1_Positive_and_Negative",
  "topicName" : "Future continuous / present perfect continuous / past perfect",
  "difficulty" : {
    "$numberDouble" : "0.0"
  },
  "retries" : {
    "$numberDouble" : "0.0"
  },
  "noScoreRetries" : {
    "$numberDouble" : "0.0"
  },
  "code" : "",
  "audioUrl" : "",
  "imageUrl" : "",
  "answerAudioUrl" : "B1.04.09.06",
  "answerImageUrl" : "",
  "miniTheory" : "",
  "successMessage" : "",
  "form" : {
    "kind" : "CLOZE",
    "incidence" : {
      "$numberDouble" : "1.0"
    },
    "label" : "",
    "name" : "",
    "sentenceParts" : [ {
      "kind" : "TEXT",
      "text" : "He",
      "options" : null
    }, {
      "kind" : "CLOZE",
      "text" : "",
      "options" : [ "hadn't drunk" ]
    }, {
      "kind" : "TEXT",
      "text" : "(not / drink) coffee.",
      "options" : null
    } ]
  }
}, {
  "_id" : {
    "$oid" : "67fab6d59930102295343247"
  },
  "id" : "67fab6d59930102295343247",
  "kind" : "CLOZE",
  "knowledgeId" : {
    "$oid" : "6814dafa7d73e7209a13d2dd"
  },
  "title" : "Positive and Negative Past Perfect Practice",
  "instructions" : "Escribe oraciones en 'past perfect'.",
  "translation" : "Ella había limpiado la mesa.",
  "theoryId" : "b1.04.Past_Perfect_Forms_1_Positive_and_Negative",
  "topicName" : "Future continuous / present perfect continuous / past perfect",
  "difficulty" : {
    "$numberDouble" : "0.0"
  },
  "retries" : {
    "$numberDouble" : "0.0"
  },
  "noScoreRetries" : {
    "$numberDouble" : "0.0"
  },
  "code" : "",
  "audioUrl" : "",
  "imageUrl" : "",
  "answerAudioUrl" : "B1.04.09.07",
  "answerImageUrl" : "",
  "miniTheory" : "",
  "successMessage" : "",
  "form" : {
    "kind" : "CLOZE",
    "incidence" : {
      "$numberDouble" : "1.0"
    },
    "label" : "",
    "name" : "",
    "sentenceParts" : [ {
      "kind" : "TEXT",
      "text" : "She",
      "options" : null
    }, {
      "kind" : "CLOZE",
      "text" : "",
      "options" : [ "had cleaned" ]
    }, {
      "kind" : "TEXT",
      "text" : "(clean) the table.",
      "options" : null
    } ]
  }
}, {
  "_id" : {
    "$oid" : "67fab6d59930102295343248"
  },
  "id" : "67fab6d59930102295343248",
  "kind" : "CLOZE",
  "knowledgeId" : {
    "$oid" : "6814dafa7d73e7209a13d2dd"
  },
  "title" : "Positive and Negative Past Perfect Practice",
  "instructions" : "Escribe oraciones en 'past perfect'.",
  "translation" : "Ella no había bebido agua.",
  "theoryId" : "b1.04.Past_Perfect_Forms_1_Positive_and_Negative",
  "topicName" : "Future continuous / present perfect continuous / past perfect",
  "difficulty" : {
    "$numberDouble" : "0.0"
  },
  "retries" : {
    "$numberDouble" : "0.0"
  },
  "noScoreRetries" : {
    "$numberDouble" : "0.0"
  },
  "code" : "",
  "audioUrl" : "",
  "imageUrl" : "",
  "answerAudioUrl" : "B1.04.09.08",
  "answerImageUrl" : "",
  "miniTheory" : "",
  "successMessage" : "",
  "form" : {
    "kind" : "CLOZE",
    "incidence" : {
      "$numberDouble" : "1.0"
    },
    "label" : "",
    "name" : "",
    "sentenceParts" : [ {
      "kind" : "TEXT",
      "text" : "She",
      "options" : null
    }, {
      "kind" : "CLOZE",
      "text" : "",
      "options" : [ "hadn't drunk" ]
    }, {
      "kind" : "TEXT",
      "text" : "(not / drink) water.",
      "options" : null
    } ]
  }
}, {
  "_id" : {
    "$oid" : "67fab6d59930102295343249"
  },
  "id" : "67fab6d59930102295343249",
  "kind" : "CLOZE",
  "knowledgeId" : {
    "$oid" : "6814dafa7d73e7209a13d2dd"
  },
  "title" : "Positive and Negative Past Perfect Practice",
  "instructions" : "Escribe oraciones en 'past perfect'.",
  "translation" : "Ellos habían visto televisión.",
  "theoryId" : "b1.04.Past_Perfect_Forms_1_Positive_and_Negative",
  "topicName" : "Future continuous / present perfect continuous / past perfect",
  "difficulty" : {
    "$numberDouble" : "0.0"
  },
  "retries" : {
    "$numberDouble" : "0.0"
  },
  "noScoreRetries" : {
    "$numberDouble" : "0.0"
  },
  "code" : "",
  "audioUrl" : "",
  "imageUrl" : "",
  "answerAudioUrl" : "B1.04.09.09",
  "answerImageUrl" : "",
  "miniTheory" : "",
  "successMessage" : "",
  "form" : {
    "kind" : "CLOZE",
    "incidence" : {
      "$numberDouble" : "1.0"
    },
    "label" : "",
    "name" : "",
    "sentenceParts" : [ {
      "kind" : "TEXT",
      "text" : "They",
      "options" : null
    }, {
      "kind" : "CLOZE",
      "text" : "",
      "options" : [ "had watched" ]
    }, {
      "kind" : "TEXT",
      "text" : "(watch) TV",
      "options" : null
    } ]
  }
}, {
  "_id" : {
    "$oid" : "67fab6d5993010229534324a"
  },
  "id" : "67fab6d5993010229534324a",
  "kind" : "CLOZE",
  "knowledgeId" : {
    "$oid" : "6814dafa7d73e7209a13d2dd"
  },
  "title" : "Positive and Negative Past Perfect Practice",
  "instructions" : "Escribe oraciones en 'past perfect'.",
  "translation" : "La niña había llorado mucho.",
  "theoryId" : "b1.04.Past_Perfect_Forms_1_Positive_and_Negative",
  "topicName" : "Future continuous / present perfect continuous / past perfect",
  "difficulty" : {
    "$numberDouble" : "0.0"
  },
  "retries" : {
    "$numberDouble" : "0.0"
  },
  "noScoreRetries" : {
    "$numberDouble" : "0.0"
  },
  "code" : "",
  "audioUrl" : "",
  "imageUrl" : "",
  "answerAudioUrl" : "B1.04.09.10",
  "answerImageUrl" : "",
  "miniTheory" : "",
  "successMessage" : "",
  "form" : {
    "kind" : "CLOZE",
    "incidence" : {
      "$numberDouble" : "1.0"
    },
    "label" : "",
    "name" : "",
    "sentenceParts" : [ {
      "kind" : "TEXT",
      "text" : "The girl",
      "options" : null
    }, {
      "kind" : "CLOZE",
      "text" : "",
      "options" : [ "had cried" ]
    }, {
      "kind" : "TEXT",
      "text" : "(cry) a lot.",
      "options" : null
    } ]
  }
}, {
  "_id" : {
    "$oid" : "67fab6d5993010229534324b"
  },
  "id" : "67fab6d5993010229534324b",
  "kind" : "CLOZE",
  "knowledgeId" : {
    "$oid" : "6814dafa7d73e7209a13d2dd"
  },
  "title" : "Positive and Negative Past Perfect Practice",
  "instructions" : "Escribe oraciones en 'past perfect'.",
  "translation" : "Yo había salido de la casa.",
  "theoryId" : "b1.04.Past_Perfect_Forms_1_Positive_and_Negative",
  "topicName" : "Future continuous / present perfect continuous / past perfect",
  "difficulty" : {
    "$numberDouble" : "0.0"
  },
  "retries" : {
    "$numberDouble" : "0.0"
  },
  "noScoreRetries" : {
    "$numberDouble" : "0.0"
  },
  "code" : "",
  "audioUrl" : "",
  "imageUrl" : "",
  "answerAudioUrl" : "B1.04.09.11",
  "answerImageUrl" : "",
  "miniTheory" : "",
  "successMessage" : "",
  "form" : {
    "kind" : "CLOZE",
    "incidence" : {
      "$numberDouble" : "1.0"
    },
    "label" : "",
    "name" : "",
    "sentenceParts" : [ {
      "kind" : "TEXT",
      "text" : "I",
      "options" : null
    }, {
      "kind" : "CLOZE",
      "text" : "",
      "options" : [ "had left" ]
    }, {
      "kind" : "TEXT",
      "text" : "(leave) the house.",
      "options" : null
    } ]
  }
}, {
  "_id" : {
    "$oid" : "67fab6d5993010229534324c"
  },
  "id" : "67fab6d5993010229534324c",
  "kind" : "CLOZE",
  "knowledgeId" : {
    "$oid" : "6814dafa7d73e7209a13d2dd"
  },
  "title" : "Positive and Negative Past Perfect Practice",
  "instructions" : "Escribe oraciones en 'past perfect'.",
  "translation" : "Yo había perdido mis llaves.",
  "theoryId" : "b1.04.Past_Perfect_Forms_1_Positive_and_Negative",
  "topicName" : "Future continuous / present perfect continuous / past perfect",
  "difficulty" : {
    "$numberDouble" : "0.0"
  },
  "retries" : {
    "$numberDouble" : "0.0"
  },
  "noScoreRetries" : {
    "$numberDouble" : "0.0"
  },
  "code" : "",
  "audioUrl" : "",
  "imageUrl" : "",
  "answerAudioUrl" : "B1.04.09.12",
  "answerImageUrl" : "",
  "miniTheory" : "",
  "successMessage" : "",
  "form" : {
    "kind" : "CLOZE",
    "incidence" : {
      "$numberDouble" : "1.0"
    },
    "label" : "",
    "name" : "",
    "sentenceParts" : [ {
      "kind" : "TEXT",
      "text" : "I",
      "options" : null
    }, {
      "kind" : "CLOZE",
      "text" : "",
      "options" : [ "had lost" ]
    }, {
      "kind" : "TEXT",
      "text" : "(lose) my keys.",
      "options" : null
    } ]
  }
}, {
  "_id" : {
    "$oid" : "67fab6d5993010229534324d"
  },
  "id" : "67fab6d5993010229534324d",
  "kind" : "CLOZE",
  "knowledgeId" : {
    "$oid" : "6814dafa7d73e7209a13d2dd"
  },
  "title" : "Positive and Negative Past Perfect Practice",
  "instructions" : "Escribe oraciones en 'past perfect'.",
  "translation" : "Lucy no había ordenado su habitación.",
  "theoryId" : "b1.04.Past_Perfect_Forms_1_Positive_and_Negative",
  "topicName" : "Future continuous / present perfect continuous / past perfect",
  "difficulty" : {
    "$numberDouble" : "0.0"
  },
  "retries" : {
    "$numberDouble" : "0.0"
  },
  "noScoreRetries" : {
    "$numberDouble" : "0.0"
  },
  "code" : "",
  "audioUrl" : "",
  "imageUrl" : "",
  "answerAudioUrl" : "B1.04.09.13",
  "answerImageUrl" : "",
  "miniTheory" : "",
  "successMessage" : "",
  "form" : {
    "kind" : "CLOZE",
    "incidence" : {
      "$numberDouble" : "1.0"
    },
    "label" : "",
    "name" : "",
    "sentenceParts" : [ {
      "kind" : "TEXT",
      "text" : "Lucy",
      "options" : null
    }, {
      "kind" : "CLOZE",
      "text" : "",
      "options" : [ "hadn't tidied" ]
    }, {
      "kind" : "TEXT",
      "text" : "(not / tidy) her bedroom.",
      "options" : null
    } ]
  }
}, {
  "_id" : {
    "$oid" : "67fab6d5993010229534324e"
  },
  "id" : "67fab6d5993010229534324e",
  "kind" : "CLOZE",
  "knowledgeId" : {
    "$oid" : "6814dafa7d73e7209a13d2dd"
  },
  "title" : "Positive and Negative Past Perfect Practice",
  "instructions" : "Escribe oraciones en 'past perfect'.",
  "translation" : "Yo había vendido mi vieja bicicleta.",
  "theoryId" : "b1.04.Past_Perfect_Forms_1_Positive_and_Negative",
  "topicName" : "Future continuous / present perfect continuous / past perfect",
  "difficulty" : {
    "$numberDouble" : "0.0"
  },
  "retries" : {
    "$numberDouble" : "0.0"
  },
  "noScoreRetries" : {
    "$numberDouble" : "0.0"
  },
  "code" : "",
  "audioUrl" : "",
  "imageUrl" : "",
  "answerAudioUrl" : "B1.04.09.14",
  "answerImageUrl" : "",
  "miniTheory" : "",
  "successMessage" : "",
  "form" : {
    "kind" : "CLOZE",
    "incidence" : {
      "$numberDouble" : "1.0"
    },
    "label" : "",
    "name" : "",
    "sentenceParts" : [ {
      "kind" : "TEXT",
      "text" : "I",
      "options" : null
    }, {
      "kind" : "CLOZE",
      "text" : "",
      "options" : [ "had sold" ]
    }, {
      "kind" : "TEXT",
      "text" : "(sell) my old bike.",
      "options" : null
    } ]
  }
}, {
  "_id" : {
    "$oid" : "67fab6d5993010229534324f"
  },
  "id" : "67fab6d5993010229534324f",
  "kind" : "CLOZE",
  "knowledgeId" : {
    "$oid" : "6814dafa7d73e7209a13d2dd"
  },
  "title" : "Positive and Negative Past Perfect Practice",
  "instructions" : "Escribe oraciones en 'past perfect'.",
  "translation" : "Ellos habían conducido hasta nuestra casa.",
  "theoryId" : "b1.04.Past_Perfect_Forms_1_Positive_and_Negative",
  "topicName" : "Future continuous / present perfect continuous / past perfect",
  "difficulty" : {
    "$numberDouble" : "0.0"
  },
  "retries" : {
    "$numberDouble" : "0.0"
  },
  "noScoreRetries" : {
    "$numberDouble" : "0.0"
  },
  "code" : "",
  "audioUrl" : "",
  "imageUrl" : "",
  "answerAudioUrl" : "B1.04.09.15",
  "answerImageUrl" : "",
  "miniTheory" : "",
  "successMessage" : "",
  "form" : {
    "kind" : "CLOZE",
    "incidence" : {
      "$numberDouble" : "1.0"
    },
    "label" : "",
    "name" : "",
    "sentenceParts" : [ {
      "kind" : "TEXT",
      "text" : "They",
      "options" : null
    }, {
      "kind" : "CLOZE",
      "text" : "",
      "options" : [ "had driven" ]
    }, {
      "kind" : "TEXT",
      "text" : "(drive) to our house.",
      "options" : null
    } ]
  }
}, {
  "_id" : {
    "$oid" : "67fab6d59930102295343250"
  },
  "id" : "67fab6d59930102295343250",
  "kind" : "CLOZE",
  "knowledgeId" : {
    "$oid" : "6814dafa7d73e7209a13d2dd"
  },
  "title" : "Positive and Negative Past Perfect Practice",
  "instructions" : "Escribe oraciones en 'past perfect'.",
  "translation" : "Nosotros habíamos hablado inglés.",
  "theoryId" : "b1.04.Past_Perfect_Forms_1_Positive_and_Negative",
  "topicName" : "Future continuous / present perfect continuous / past perfect",
  "difficulty" : {
    "$numberDouble" : "0.0"
  },
  "retries" : {
    "$numberDouble" : "0.0"
  },
  "noScoreRetries" : {
    "$numberDouble" : "0.0"
  },
  "code" : "",
  "audioUrl" : "",
  "imageUrl" : "",
  "answerAudioUrl" : "B1.04.09.16",
  "answerImageUrl" : "",
  "miniTheory" : "",
  "successMessage" : "",
  "form" : {
    "kind" : "CLOZE",
    "incidence" : {
      "$numberDouble" : "1.0"
    },
    "label" : "",
    "name" : "",
    "sentenceParts" : [ {
      "kind" : "TEXT",
      "text" : "We",
      "options" : null
    }, {
      "kind" : "CLOZE",
      "text" : "",
      "options" : [ "had spoken" ]
    }, {
      "kind" : "TEXT",
      "text" : "(speak) English.",
      "options" : null
    } ]
  }
}, {
  "_id" : {
    "$oid" : "67fab6d59930102295343251"
  },
  "id" : "67fab6d59930102295343251",
  "kind" : "CLOZE",
  "knowledgeId" : {
    "$oid" : "6814dafa7d73e7209a13d2dd"
  },
  "title" : "Positive and Negative Past Perfect Practice",
  "instructions" : "Escribe oraciones en 'past perfect'.",
  "translation" : "Los estudiantes no habían corrido desde el parque.",
  "theoryId" : "b1.04.Past_Perfect_Forms_1_Positive_and_Negative",
  "topicName" : "Future continuous / present perfect continuous / past perfect",
  "difficulty" : {
    "$numberDouble" : "0.0"
  },
  "retries" : {
    "$numberDouble" : "0.0"
  },
  "noScoreRetries" : {
    "$numberDouble" : "0.0"
  },
  "code" : "",
  "audioUrl" : "",
  "imageUrl" : "",
  "answerAudioUrl" : "B1.04.09.17",
  "answerImageUrl" : "",
  "miniTheory" : "",
  "successMessage" : "",
  "form" : {
    "kind" : "CLOZE",
    "incidence" : {
      "$numberDouble" : "1.0"
    },
    "label" : "",
    "name" : "",
    "sentenceParts" : [ {
      "kind" : "TEXT",
      "text" : "The students",
      "options" : null
    }, {
      "kind" : "CLOZE",
      "text" : "",
      "options" : [ "hadn't run" ]
    }, {
      "kind" : "TEXT",
      "text" : "(not / run) from the park.",
      "options" : null
    } ]
  }
}, {
  "_id" : {
    "$oid" : "67fab6d59930102295343252"
  },
  "id" : "67fab6d59930102295343252",
  "kind" : "CLOZE",
  "knowledgeId" : {
    "$oid" : "6814dafa7d73e7209a13d2dd"
  },
  "title" : "Positive and Negative Past Perfect Practice",
  "instructions" : "Escribe oraciones en 'past perfect'.",
  "translation" : "Ella no había llamado a Peter.",
  "theoryId" : "b1.04.Past_Perfect_Forms_1_Positive_and_Negative",
  "topicName" : "Future continuous / present perfect continuous / past perfect",
  "difficulty" : {
    "$numberDouble" : "0.0"
  },
  "retries" : {
    "$numberDouble" : "0.0"
  },
  "noScoreRetries" : {
    "$numberDouble" : "0.0"
  },
  "code" : "",
  "audioUrl" : "",
  "imageUrl" : "",
  "answerAudioUrl" : "B1.04.09.18",
  "answerImageUrl" : "",
  "miniTheory" : "",
  "successMessage" : "",
  "form" : {
    "kind" : "CLOZE",
    "incidence" : {
      "$numberDouble" : "1.0"
    },
    "label" : "",
    "name" : "",
    "sentenceParts" : [ {
      "kind" : "TEXT",
      "text" : "She",
      "options" : null
    }, {
      "kind" : "CLOZE",
      "text" : "",
      "options" : [ "hadn't phoned" ]
    }, {
      "kind" : "TEXT",
      "text" : "(not / phone) Peter.",
      "options" : null
    } ]
  }
}, {
  "_id" : {
    "$oid" : "67fab6d59930102295343253"
  },
  "id" : "67fab6d59930102295343253",
  "kind" : "CLOZE",
  "knowledgeId" : {
    "$oid" : "6814dafa7d73e7209a13d2dd"
  },
  "title" : "Positive and Negative Past Perfect Practice",
  "instructions" : "Escribe oraciones en 'past perfect'.",
  "translation" : "Ellos no habían dormido bien.",
  "theoryId" : "b1.04.Past_Perfect_Forms_1_Positive_and_Negative",
  "topicName" : "Future continuous / present perfect continuous / past perfect",
  "difficulty" : {
    "$numberDouble" : "0.0"
  },
  "retries" : {
    "$numberDouble" : "0.0"
  },
  "noScoreRetries" : {
    "$numberDouble" : "0.0"
  },
  "code" : "",
  "audioUrl" : "",
  "imageUrl" : "",
  "answerAudioUrl" : "B1.04.09.19",
  "answerImageUrl" : "",
  "miniTheory" : "",
  "successMessage" : "",
  "form" : {
    "kind" : "CLOZE",
    "incidence" : {
      "$numberDouble" : "1.0"
    },
    "label" : "",
    "name" : "",
    "sentenceParts" : [ {
      "kind" : "TEXT",
      "text" : "They",
      "options" : null
    }, {
      "kind" : "CLOZE",
      "text" : "",
      "options" : [ "hadn't slept" ]
    }, {
      "kind" : "TEXT",
      "text" : "(not / sleep) well.",
      "options" : null
    } ]
  }
}, {
  "_id" : {
    "$oid" : "67fab6d59930102295343254"
  },
  "id" : "67fab6d59930102295343254",
  "kind" : "CLOZE",
  "knowledgeId" : {
    "$oid" : "6814dafa7d73e7209a13d2dd"
  },
  "title" : "Positive and Negative Past Perfect Practice",
  "instructions" : "Escribe oraciones en 'past perfect'.",
  "translation" : "Nosotros no habíamos logrado cerrar la ventana.",
  "theoryId" : "b1.04.Past_Perfect_Forms_1_Positive_and_Negative",
  "topicName" : "Future continuous / present perfect continuous / past perfect",
  "difficulty" : {
    "$numberDouble" : "0.0"
  },
  "retries" : {
    "$numberDouble" : "0.0"
  },
  "noScoreRetries" : {
    "$numberDouble" : "0.0"
  },
  "code" : "",
  "audioUrl" : "",
  "imageUrl" : "",
  "answerAudioUrl" : "B1.04.09.20",
  "answerImageUrl" : "",
  "miniTheory" : "",
  "successMessage" : "",
  "form" : {
    "kind" : "CLOZE",
    "incidence" : {
      "$numberDouble" : "1.0"
    },
    "label" : "",
    "name" : "",
    "sentenceParts" : [ {
      "kind" : "TEXT",
      "text" : "We",
      "options" : null
    }, {
      "kind" : "CLOZE",
      "text" : "",
      "options" : [ "hadn't managed" ]
    }, {
      "kind" : "TEXT",
      "text" : "(not / manage) to close the window.",
      "options" : null
    } ]
  }
} ]