[
  {
    "_id": {
      "$oid": "67fab6d599301022953423b7"
    },
    "kind": "CLOZE",
    "audioUrl": "",
    "miniTheory": "",
    "answerImageUrl": "",
    "answerAudioUrl": "A1.07.04.01",
    "code": "",
    "difficulty": {
      "$numberDouble": "0.0"
    },
    "title": "Choosing Between Much and Many",
    "form": {
      "kind": "CLOZE",
      "incidence": {
        "$numberDouble": "1.0"
      },
      "label": "",
      "name": "",
      "sentenceParts": [
        {
          "kind": "TEXT",
          "text": "We don't spend",
          "options": null
        },
        {
          "kind": "CLOZE",
          "text": "",
          "options": [
            "much"
          ]
        },
        {
          "kind": "TEXT",
          "text": "energy.",
          "options": null
        }
      ]
    },
    "translation": "No gastamos mucha energía.",
    "id": "67fab6d599301022953423b7",
    "retries": {
      "$numberDouble": "0.0"
    },
    "imageUrl": "",
    "knowledgeId": {
      "$oid": "6814dafa7d73e7209a13d3cf"
    },
    "noScoreRetries": {
      "$numberDouble": "0.0"
    },
    "instructions": "Completa los espacios en blanco con 'much' o 'many'.",
    "theoryId": "a1.07.Much_Many",
    "successMessage": "",
    "topicName": "Determiners"
  },
  {
    "_id": {
      "$oid": "67fab6d599301022953423b8"
    },
    "id": "67fab6d599301022953423b8",
    "translation": "No beben mucho café.",
    "answerAudioUrl": "A1.07.04.02",
    "successMessage": "",
    "answerImageUrl": "",
    "theoryId": "a1.07.Much_Many",
    "miniTheory": "",
    "code": "",
    "difficulty": {
      "$numberDouble": "0.0"
    },
    "form": {
      "sentenceParts": [
        {
          "kind": "TEXT",
          "text": "They don't drink",
          "options": null
        },
        {
          "text": "",
          "options": [
            "much"
          ],
          "kind": "CLOZE"
        },
        {
          "kind": "TEXT",
          "text": "coffee.",
          "options": null
        }
      ],
      "kind": "CLOZE",
      "incidence": {
        "$numberDouble": "1.0"
      },
      "label": "",
      "name": ""
    },
    "noScoreRetries": {
      "$numberDouble": "0.0"
    },
    "title": "Choosing Between Much and Many",
    "instructions": "Completa los espacios en blanco con 'much' o 'many'.",
    "imageUrl": "",
    "audioUrl": "",
    "kind": "CLOZE",
    "knowledgeId": {
      "$oid": "6814dafa7d73e7209a13d3cf"
    },
    "retries": {
      "$numberDouble": "0.0"
    },
    "topicName": "Determiners"
  },
  {
    "_id": {
      "$oid": "67fab6d599301022953423b9"
    },
    "id": "67fab6d599301022953423b9",
    "code": "",
    "kind": "CLOZE",
    "difficulty": {
      "$numberDouble": "0.0"
    },
    "imageUrl": "",
    "successMessage": "",
    "answerImageUrl": "",
    "knowledgeId": {
      "$oid": "6814dafa7d73e7209a13d3cf"
    },
    "retries": {
      "$numberDouble": "0.0"
    },
    "audioUrl": "",
    "miniTheory": "",
    "theoryId": "a1.07.Much_Many",
    "translation": "¿Requiere ella mucho esfuerzo?",
    "answerAudioUrl": "A1.07.04.03",
    "noScoreRetries": {
      "$numberDouble": "0.0"
    },
    "title": "Choosing Between Much and Many",
    "instructions": "Completa los espacios en blanco con 'much' o 'many'.",
    "form": {
      "label": "",
      "name": "",
      "sentenceParts": [
        {
          "kind": "TEXT",
          "text": "Does she require",
          "options": null
        },
        {
          "kind": "CLOZE",
          "text": "",
          "options": [
            "much"
          ]
        },
        {
          "kind": "TEXT",
          "text": "effort?",
          "options": null
        }
      ],
      "kind": "CLOZE",
      "incidence": {
        "$numberDouble": "1.0"
      }
    },
    "topicName": "Determiners"
  },
  {
    "_id": {
      "$oid": "67fab6d599301022953423ba"
    },
    "noScoreRetries": {
      "$numberDouble": "0.0"
    },
    "instructions": "Completa los espacios en blanco con 'much' o 'many'.",
    "audioUrl": "",
    "miniTheory": "",
    "answerImageUrl": "",
    "id": "67fab6d599301022953423ba",
    "kind": "CLOZE",
    "knowledgeId": {
      "$oid": "6814dafa7d73e7209a13d3cf"
    },
    "theoryId": "a1.07.Much_Many",
    "translation": "No compran muchos libros.",
    "difficulty": {
      "$numberDouble": "0.0"
    },
    "retries": {
      "$numberDouble": "0.0"
    },
    "title": "Choosing Between Much and Many",
    "form": {
      "label": "",
      "name": "",
      "sentenceParts": [
        {
          "kind": "TEXT",
          "text": "They don't buy",
          "options": null
        },
        {
          "options": [
            "many"
          ],
          "kind": "CLOZE",
          "text": ""
        },
        {
          "kind": "TEXT",
          "text": "books.",
          "options": null
        }
      ],
      "kind": "CLOZE",
      "incidence": {
        "$numberDouble": "1.0"
      }
    },
    "imageUrl": "",
    "code": "",
    "successMessage": "",
    "answerAudioUrl": "A1.07.04.04",
    "topicName": "Determiners"
  },
  {
    "_id": {
      "$oid": "67fab6d599301022953423bb"
    },
    "translation": "No usan mucho jabón.",
    "miniTheory": "",
    "code": "",
    "kind": "CLOZE",
    "difficulty": {
      "$numberDouble": "0.0"
    },
    "retries": {
      "$numberDouble": "0.0"
    },
    "knowledgeId": {
      "$oid": "6814dafa7d73e7209a13d3cf"
    },
    "theoryId": "a1.07.Much_Many",
    "imageUrl": "",
    "successMessage": "",
    "answerAudioUrl": "A1.07.04.05",
    "id": "67fab6d599301022953423bb",
    "noScoreRetries": {
      "$numberDouble": "0.0"
    },
    "form": {
      "incidence": {
        "$numberDouble": "1.0"
      },
      "label": "",
      "name": "",
      "sentenceParts": [
        {
          "text": "They don't use",
          "options": null,
          "kind": "TEXT"
        },
        {
          "kind": "CLOZE",
          "text": "",
          "options": [
            "much"
          ]
        },
        {
          "kind": "TEXT",
          "text": "soap.",
          "options": null
        }
      ],
      "kind": "CLOZE"
    },
    "audioUrl": "",
    "title": "Choosing Between Much and Many",
    "instructions": "Completa los espacios en blanco con 'much' o 'many'.",
    "answerImageUrl": "",
    "topicName": "Determiners"
  },
  {
    "_id": {
      "$oid": "67fab6d599301022953423bc"
    },
    "instructions": "Completa los espacios en blanco con 'much' o 'many'.",
    "miniTheory": "",
    "answerImageUrl": "",
    "id": "67fab6d599301022953423bc",
    "kind": "CLOZE",
    "retries": {
      "$numberDouble": "0.0"
    },
    "title": "Choosing Between Much and Many",
    "theoryId": "a1.07.Much_Many",
    "imageUrl": "",
    "difficulty": {
      "$numberDouble": "0.0"
    },
    "noScoreRetries": {
      "$numberDouble": "0.0"
    },
    "audioUrl": "",
    "translation": "¿Tienen mucha lectura los estudiantes?",
    "code": "",
    "knowledgeId": {
      "$oid": "6814dafa7d73e7209a13d3cf"
    },
    "form": {
      "kind": "CLOZE",
      "incidence": {
        "$numberDouble": "1.0"
      },
      "label": "",
      "name": "",
      "sentenceParts": [
        {
          "text": "Do the students have",
          "options": null,
          "kind": "TEXT"
        },
        {
          "kind": "CLOZE",
          "text": "",
          "options": [
            "much"
          ]
        },
        {
          "kind": "TEXT",
          "text": "reading?",
          "options": null
        }
      ]
    },
    "successMessage": "",
    "answerAudioUrl": "A1.07.04.06",
    "topicName": "Determiners"
  },
  {
    "_id": {
      "$oid": "67fab6d599301022953423bd"
    },
    "kind": "CLOZE",
    "difficulty": {
      "$numberDouble": "0.0"
    },
    "theoryId": "a1.07.Much_Many",
    "answerAudioUrl": "A1.07.04.07",
    "id": "67fab6d599301022953423bd",
    "retries": {
      "$numberDouble": "0.0"
    },
    "title": "Choosing Between Much and Many",
    "imageUrl": "",
    "answerImageUrl": "",
    "instructions": "Completa los espacios en blanco con 'much' o 'many'.",
    "translation": "No tengo muchos sombreros.",
    "successMessage": "",
    "miniTheory": "",
    "audioUrl": "",
    "code": "",
    "knowledgeId": {
      "$oid": "6814dafa7d73e7209a13d3cf"
    },
    "noScoreRetries": {
      "$numberDouble": "0.0"
    },
    "form": {
      "label": "",
      "name": "",
      "sentenceParts": [
        {
          "kind": "TEXT",
          "text": "I don't own",
          "options": null
        },
        {
          "kind": "CLOZE",
          "text": "",
          "options": [
            "many"
          ]
        },
        {
          "kind": "TEXT",
          "text": "hats.",
          "options": null
        }
      ],
      "kind": "CLOZE",
      "incidence": {
        "$numberDouble": "1.0"
      }
    },
    "topicName": "Determiners"
  },
  {
    "_id": {
      "$oid": "67fab6d599301022953423be"
    },
    "answerAudioUrl": "A1.07.04.08",
    "id": "67fab6d599301022953423be",
    "translation": "David no tiene mucha responsabilidad hoy en día.",
    "answerImageUrl": "",
    "knowledgeId": {
      "$oid": "6814dafa7d73e7209a13d3cf"
    },
    "difficulty": {
      "$numberDouble": "0.0"
    },
    "retries": {
      "$numberDouble": "0.0"
    },
    "noScoreRetries": {
      "$numberDouble": "0.0"
    },
    "theoryId": "a1.07.Much_Many",
    "imageUrl": "",
    "code": "",
    "kind": "CLOZE",
    "audioUrl": "",
    "miniTheory": "",
    "form": {
      "label": "",
      "name": "",
      "sentenceParts": [
        {
          "kind": "TEXT",
          "text": "David doesn't have",
          "options": null
        },
        {
          "kind": "CLOZE",
          "text": "",
          "options": [
            "much"
          ]
        },
        {
          "kind": "TEXT",
          "text": "responsibility nowadays.",
          "options": null
        }
      ],
      "kind": "CLOZE",
      "incidence": {
        "$numberDouble": "1.0"
      }
    },
    "successMessage": "",
    "title": "Choosing Between Much and Many",
    "instructions": "Completa los espacios en blanco con 'much' o 'many'.",
    "topicName": "Determiners"
  },
  {
    "_id": {
      "$oid": "67fab6d599301022953423bf"
    },
    "kind": "CLOZE",
    "knowledgeId": {
      "$oid": "6814dafa7d73e7209a13d3cf"
    },
    "noScoreRetries": {
      "$numberDouble": "0.0"
    },
    "instructions": "Completa los espacios en blanco con 'much' o 'many'.",
    "title": "Choosing Between Much and Many",
    "form": {
      "kind": "CLOZE",
      "incidence": {
        "$numberDouble": "1.0"
      },
      "label": "",
      "name": "",
      "sentenceParts": [
        {
          "kind": "TEXT",
          "text": "Does he explore",
          "options": null
        },
        {
          "kind": "CLOZE",
          "text": "",
          "options": [
            "many"
          ]
        },
        {
          "text": "countries?",
          "options": null,
          "kind": "TEXT"
        }
      ]
    },
    "successMessage": "",
    "answerAudioUrl": "A1.07.04.09",
    "id": "67fab6d599301022953423bf",
    "code": "",
    "retries": {
      "$numberDouble": "0.0"
    },
    "audioUrl": "",
    "answerImageUrl": "",
    "difficulty": {
      "$numberDouble": "0.0"
    },
    "theoryId": "a1.07.Much_Many",
    "imageUrl": "",
    "translation": "¿Explora él muchos países?",
    "miniTheory": "",
    "topicName": "Determiners"
  },
  {
    "_id": {
      "$oid": "67fab6d599301022953423c0"
    },
    "kind": "CLOZE",
    "knowledgeId": {
      "$oid": "6814dafa7d73e7209a13d3cf"
    },
    "audioUrl": "",
    "answerImageUrl": "",
    "noScoreRetries": {
      "$numberDouble": "0.0"
    },
    "instructions": "Completa los espacios en blanco con 'much' o 'many'.",
    "form": {
      "kind": "CLOZE",
      "incidence": {
        "$numberDouble": "1.0"
      },
      "label": "",
      "name": "",
      "sentenceParts": [
        {
          "kind": "TEXT",
          "text": "We don't like to see",
          "options": null
        },
        {
          "kind": "CLOZE",
          "text": "",
          "options": [
            "many"
          ]
        },
        {
          "kind": "TEXT",
          "text": "animals.",
          "options": null
        }
      ]
    },
    "theoryId": "a1.07.Much_Many",
    "successMessage": "",
    "answerAudioUrl": "A1.07.04.10",
    "code": "",
    "difficulty": {
      "$numberDouble": "0.0"
    },
    "title": "Choosing Between Much and Many",
    "imageUrl": "",
    "miniTheory": "",
    "id": "67fab6d599301022953423c0",
    "retries": {
      "$numberDouble": "0.0"
    },
    "translation": "No nos gusta ver muchos animales.",
    "topicName": "Determiners"
  },
  {
    "_id": {
      "$oid": "67fab6d599301022953423c1"
    },
    "noScoreRetries": {
      "$numberDouble": "0.0"
    },
    "title": "Choosing Between Much and Many",
    "imageUrl": "",
    "successMessage": "",
    "id": "67fab6d599301022953423c1",
    "kind": "CLOZE",
    "retries": {
      "$numberDouble": "0.0"
    },
    "form": {
      "label": "",
      "name": "",
      "sentenceParts": [
        {
          "kind": "TEXT",
          "text": "She doesn't have",
          "options": null
        },
        {
          "kind": "CLOZE",
          "text": "",
          "options": [
            "much"
          ]
        },
        {
          "kind": "TEXT",
          "text": "patience.",
          "options": null
        }
      ],
      "kind": "CLOZE",
      "incidence": {
        "$numberDouble": "1.0"
      }
    },
    "translation": "Ella no tiene mucha paciencia.",
    "difficulty": {
      "$numberDouble": "0.0"
    },
    "theoryId": "a1.07.Much_Many",
    "answerImageUrl": "",
    "answerAudioUrl": "A1.07.04.11",
    "code": "",
    "knowledgeId": {
      "$oid": "6814dafa7d73e7209a13d3cf"
    },
    "instructions": "Completa los espacios en blanco con 'much' o 'many'.",
    "audioUrl": "",
    "miniTheory": "",
    "topicName": "Determiners"
  },
  {
    "_id": {
      "$oid": "67fab6d599301022953423c2"
    },
    "audioUrl": "",
    "successMessage": "",
    "noScoreRetries": {
      "$numberDouble": "0.0"
    },
    "retries": {
      "$numberDouble": "0.0"
    },
    "instructions": "Completa los espacios en blanco con 'much' o 'many'.",
    "form": {
      "sentenceParts": [
        {
          "kind": "TEXT",
          "text": "She doesn't read",
          "options": null
        },
        {
          "kind": "CLOZE",
          "text": "",
          "options": [
            "many"
          ]
        },
        {
          "kind": "TEXT",
          "text": "comics.",
          "options": null
        }
      ],
      "kind": "CLOZE",
      "incidence": {
        "$numberDouble": "1.0"
      },
      "label": "",
      "name": ""
    },
    "theoryId": "a1.07.Much_Many",
    "imageUrl": "",
    "translation": "Ella no lee muchos cómics.",
    "answerImageUrl": "",
    "difficulty": {
      "$numberDouble": "0.0"
    },
    "knowledgeId": {
      "$oid": "6814dafa7d73e7209a13d3cf"
    },
    "code": "",
    "kind": "CLOZE",
    "title": "Choosing Between Much and Many",
    "miniTheory": "",
    "answerAudioUrl": "A1.07.04.12",
    "id": "67fab6d599301022953423c2",
    "topicName": "Determiners"
  },
  {
    "_id": {
      "$oid": "67fab6d599301022953423c3"
    },
    "id": "67fab6d599301022953423c3",
    "miniTheory": "",
    "difficulty": {
      "$numberDouble": "0.0"
    },
    "imageUrl": "",
    "successMessage": "",
    "code": "",
    "kind": "CLOZE",
    "title": "Choosing Between Much and Many",
    "instructions": "Completa los espacios en blanco con 'much' o 'many'.",
    "form": {
      "name": "",
      "sentenceParts": [
        {
          "kind": "TEXT",
          "text": "Does he add",
          "options": null
        },
        {
          "kind": "CLOZE",
          "text": "",
          "options": [
            "much"
          ]
        },
        {
          "kind": "TEXT",
          "text": "salt?",
          "options": null
        }
      ],
      "kind": "CLOZE",
      "incidence": {
        "$numberDouble": "1.0"
      },
      "label": ""
    },
    "theoryId": "a1.07.Much_Many",
    "translation": "¿Añade él mucha sal?",
    "answerAudioUrl": "A1.07.04.13",
    "retries": {
      "$numberDouble": "0.0"
    },
    "noScoreRetries": {
      "$numberDouble": "0.0"
    },
    "answerImageUrl": "",
    "knowledgeId": {
      "$oid": "6814dafa7d73e7209a13d3cf"
    },
    "audioUrl": "",
    "topicName": "Determiners"
  },
  {
    "_id": {
      "$oid": "67fab6d599301022953423c4"
    },
    "id": "67fab6d599301022953423c4",
    "knowledgeId": {
      "$oid": "6814dafa7d73e7209a13d3cf"
    },
    "form": {
      "sentenceParts": [
        {
          "kind": "TEXT",
          "text": "Is there",
          "options": null
        },
        {
          "kind": "CLOZE",
          "text": "",
          "options": [
            "much"
          ]
        },
        {
          "kind": "TEXT",
          "text": "snow today?",
          "options": null
        }
      ],
      "kind": "CLOZE",
      "incidence": {
        "$numberDouble": "1.0"
      },
      "label": "",
      "name": ""
    },
    "successMessage": "",
    "retries": {
      "$numberDouble": "0.0"
    },
    "instructions": "Completa los espacios en blanco con 'much' o 'many'.",
    "theoryId": "a1.07.Much_Many",
    "translation": "¿Hay mucha nieve hoy?",
    "miniTheory": "",
    "answerImageUrl": "",
    "kind": "CLOZE",
    "difficulty": {
      "$numberDouble": "0.0"
    },
    "title": "Choosing Between Much and Many",
    "imageUrl": "",
    "audioUrl": "",
    "code": "",
    "noScoreRetries": {
      "$numberDouble": "0.0"
    },
    "answerAudioUrl": "A1.07.04.14",
    "topicName": "Determiners"
  },
  {
    "_id": {
      "$oid": "67fab6d599301022953423c5"
    },
    "knowledgeId": {
      "$oid": "6814dafa7d73e7209a13d3cf"
    },
    "retries": {
      "$numberDouble": "0.0"
    },
    "answerImageUrl": "",
    "code": "",
    "title": "Choosing Between Much and Many",
    "theoryId": "a1.07.Much_Many",
    "miniTheory": "",
    "answerAudioUrl": "A1.07.04.15",
    "successMessage": "",
    "id": "67fab6d599301022953423c5",
    "kind": "CLOZE",
    "difficulty": {
      "$numberDouble": "0.0"
    },
    "noScoreRetries": {
      "$numberDouble": "0.0"
    },
    "form": {
      "sentenceParts": [
        {
          "text": "Do you know",
          "options": null,
          "kind": "TEXT"
        },
        {
          "kind": "CLOZE",
          "text": "",
          "options": [
            "many"
          ]
        },
        {
          "kind": "TEXT",
          "text": "actors?",
          "options": null
        }
      ],
      "kind": "CLOZE",
      "incidence": {
        "$numberDouble": "1.0"
      },
      "label": "",
      "name": ""
    },
    "translation": "¿Conoces a muchos actores?",
    "instructions": "Completa los espacios en blanco con 'much' o 'many'.",
    "imageUrl": "",
    "audioUrl": "",
    "topicName": "Determiners"
  },
  {
    "_id": {
      "$oid": "67fab6d599301022953423c6"
    },
    "successMessage": "",
    "kind": "CLOZE",
    "retries": {
      "$numberDouble": "0.0"
    },
    "translation": "¿Dan los profesores muchos exámenes?",
    "instructions": "Completa los espacios en blanco con 'much' o 'many'.",
    "theoryId": "a1.07.Much_Many",
    "imageUrl": "",
    "id": "67fab6d599301022953423c6",
    "noScoreRetries": {
      "$numberDouble": "0.0"
    },
    "title": "Choosing Between Much and Many",
    "audioUrl": "",
    "answerAudioUrl": "A1.07.04.16",
    "knowledgeId": {
      "$oid": "6814dafa7d73e7209a13d3cf"
    },
    "difficulty": {
      "$numberDouble": "0.0"
    },
    "form": {
      "kind": "CLOZE",
      "incidence": {
        "$numberDouble": "1.0"
      },
      "label": "",
      "name": "",
      "sentenceParts": [
        {
          "kind": "TEXT",
          "text": "Do the teachers give",
          "options": null
        },
        {
          "kind": "CLOZE",
          "text": "",
          "options": [
            "many"
          ]
        },
        {
          "kind": "TEXT",
          "text": "tests?",
          "options": null
        }
      ]
    },
    "code": "",
    "miniTheory": "",
    "answerImageUrl": "",
    "topicName": "Determiners"
  },
  {
    "_id": {
      "$oid": "67fab6d599301022953423c7"
    },
    "difficulty": {
      "$numberDouble": "0.0"
    },
    "retries": {
      "$numberDouble": "0.0"
    },
    "imageUrl": "",
    "translation": "¿Escribe ella muchas cartas?",
    "successMessage": "",
    "answerImageUrl": "",
    "id": "67fab6d599301022953423c7",
    "knowledgeId": {
      "$oid": "6814dafa7d73e7209a13d3cf"
    },
    "noScoreRetries": {
      "$numberDouble": "0.0"
    },
    "audioUrl": "",
    "kind": "CLOZE",
    "instructions": "Completa los espacios en blanco con 'much' o 'many'.",
    "form": {
      "kind": "CLOZE",
      "incidence": {
        "$numberDouble": "1.0"
      },
      "label": "",
      "name": "",
      "sentenceParts": [
        {
          "kind": "TEXT",
          "text": "Does she write",
          "options": null
        },
        {
          "kind": "CLOZE",
          "text": "",
          "options": [
            "many"
          ]
        },
        {
          "text": "letters?",
          "options": null,
          "kind": "TEXT"
        }
      ]
    },
    "theoryId": "a1.07.Much_Many",
    "code": "",
    "title": "Choosing Between Much and Many",
    "miniTheory": "",
    "answerAudioUrl": "A1.07.04.17",
    "topicName": "Determiners"
  },
  {
    "_id": {
      "$oid": "67fab6d599301022953423c8"
    },
    "knowledgeId": {
      "$oid": "6814dafa7d73e7209a13d3cf"
    },
    "difficulty": {
      "$numberDouble": "0.0"
    },
    "imageUrl": "",
    "id": "67fab6d599301022953423c8",
    "title": "Choosing Between Much and Many",
    "translation": "¿Te queda mucho jugo?",
    "successMessage": "",
    "answerImageUrl": "",
    "code": "",
    "instructions": "Completa los espacios en blanco con 'much' o 'many'.",
    "form": {
      "incidence": {
        "$numberDouble": "1.0"
      },
      "label": "",
      "name": "",
      "sentenceParts": [
        {
          "kind": "TEXT",
          "text": "Do you have",
          "options": null
        },
        {
          "kind": "CLOZE",
          "text": "",
          "options": [
            "much"
          ]
        },
        {
          "kind": "TEXT",
          "text": "juice remaining?",
          "options": null
        }
      ],
      "kind": "CLOZE"
    },
    "miniTheory": "",
    "kind": "CLOZE",
    "retries": {
      "$numberDouble": "0.0"
    },
    "noScoreRetries": {
      "$numberDouble": "0.0"
    },
    "theoryId": "a1.07.Much_Many",
    "audioUrl": "",
    "answerAudioUrl": "A1.07.04.18",
    "topicName": "Determiners"
  },
  {
    "_id": {
      "$oid": "67fab6d599301022953423c9"
    },
    "code": "",
    "kind": "CLOZE",
    "title": "Choosing Between Much and Many",
    "instructions": "Completa los espacios en blanco con 'much' o 'many'.",
    "successMessage": "",
    "retries": {
      "$numberDouble": "0.0"
    },
    "noScoreRetries": {
      "$numberDouble": "0.0"
    },
    "form": {
      "label": "",
      "name": "",
      "sentenceParts": [
        {
          "kind": "TEXT",
          "text": "Do you prepare",
          "options": null
        },
        {
          "text": "",
          "options": [
            "many"
          ],
          "kind": "CLOZE"
        },
        {
          "kind": "TEXT",
          "text": "cookies?",
          "options": null
        }
      ],
      "kind": "CLOZE",
      "incidence": {
        "$numberDouble": "1.0"
      }
    },
    "answerAudioUrl": "A1.07.04.19",
    "id": "67fab6d599301022953423c9",
    "knowledgeId": {
      "$oid": "6814dafa7d73e7209a13d3cf"
    },
    "difficulty": {
      "$numberDouble": "0.0"
    },
    "audioUrl": "",
    "translation": "¿Preparas muchas galletas?",
    "theoryId": "a1.07.Much_Many",
    "imageUrl": "",
    "miniTheory": "",
    "answerImageUrl": "",
    "topicName": "Determiners"
  },
  {
    "_id": {
      "$oid": "67fab6d599301022953423ca"
    },
    "kind": "CLOZE",
    "knowledgeId": {
      "$oid": "6814dafa7d73e7209a13d3cf"
    },
    "title": "Choosing Between Much and Many",
    "id": "67fab6d599301022953423ca",
    "retries": {
      "$numberDouble": "0.0"
    },
    "form": {
      "incidence": {
        "$numberDouble": "1.0"
      },
      "label": "",
      "name": "",
      "sentenceParts": [
        {
          "kind": "TEXT",
          "text": "The parents don't buy",
          "options": null
        },
        {
          "kind": "CLOZE",
          "text": "",
          "options": [
            "many"
          ]
        },
        {
          "kind": "TEXT",
          "text": "toys.",
          "options": null
        }
      ],
      "kind": "CLOZE"
    },
    "theoryId": "a1.07.Much_Many",
    "answerAudioUrl": "A1.07.04.20",
    "code": "",
    "noScoreRetries": {
      "$numberDouble": "0.0"
    },
    "imageUrl": "",
    "successMessage": "",
    "miniTheory": "",
    "answerImageUrl": "",
    "difficulty": {
      "$numberDouble": "0.0"
    },
    "instructions": "Completa los espacios en blanco con 'much' o 'many'.",
    "audioUrl": "",
    "translation": "Los padres no compran muchos juguetes.",
    "topicName": "Determiners"
  }
]
